{
  "schemaVersion": 1,
  "videoId": "FV6PzZlVOKA",
  "topics": [
    "dutch-navy",
    "destroyers",
    "interwar-navy",
    "naval-procurement",
    "naval-policy",
    "strategic-deterrence",
    "second-world-war",
    "ship-design",
    "force-structure"
  ],
  "segments": [
    {
      "id": "dutch-interwar-destroyer-deterrence-gap",
      "slug": "dutch-interwar-destroyer-deterrence-gap",
      "title": "Dutch interwar destroyer debate exposed a deterrence gap",
      "kind": "notable_point",
      "start": "0:39",
      "end": "34:54",
      "topics": [
        "dutch-navy",
        "destroyers",
        "interwar-navy",
        "naval-procurement",
        "naval-policy",
        "strategic-deterrence",
        "second-world-war",
        "ship-design",
        "force-structure"
      ],
      "summary": "The lecture links the failed 1923 Dutch naval law, East Indies deterrence, and too few Admiral de Ruyter-class destroyers to the Netherlands' later wartime vulnerability.",
      "body": "Dutch interwar politics treated naval spending as a budget and left-right fight, leaving a small destroyer force to cover both home waters and the Dutch East Indies. Dr. Clarke contrasts the inadequate prewar Wolf/Fret-class ships with the capable but undernumbered Admiral de Ruyter class, then uses their 1940-1942 losses to argue that deterrence and force slack had been underfunded.",
      "evidence": [
        {
          "start": "0:39",
          "end": "3:03",
          "note": "The opening frames the 1923 naval law crisis and lists the proposed submarines, cruisers, fleet torpedo vessels, destroyers, aircraft, and six-year funding."
        },
        {
          "start": "5:43",
          "end": "8:57",
          "note": "The transcript argues the Dutch sought guarantees while needing real deterrent capability, and ties the proposed force increase to the Dutch East Indies and Japan's rise."
        },
        {
          "start": "21:43",
          "end": "24:08",
          "note": "The Admiral de Ruyter class is described as a major improvement with useful weapons, speed, range, and aviation fit, but only eight ships were built."
        },
        {
          "start": "24:13",
          "end": "28:41",
          "note": "The wartime fate section notes that none of the class remained operational after mid-1942 and argues the 1923 law would not have saved everything but would have improved the position."
        },
        {
          "start": "29:45",
          "end": "34:54",
          "note": "The conclusion warns against planning with certainty about the future and says the Dutch had useful destroyers but not enough of them for home waters and the East Indies."
        }
      ],
      "videoId": "FV6PzZlVOKA",
      "sourcePath": "src/transcripts/txt/2026-04-22_T18-30-06_the-dutch-interwar-destroyer-debate_FV6PzZlVOKA.txt"
    }
  ]
}
